backprop/__init__.py
backprop/core.py
backprop/models/__init__.py
backprop/models/auto_model.py
backprop/models/generic_models.py
backprop/models/bart_large_mnli/__init__.py
backprop/models/bart_large_mnli/model.py
backprop/models/clip/__init__.py
backprop/models/clip/clip.py
backprop/models/clip/model.py
backprop/models/clip/models_list.py
backprop/models/clip/module.py
backprop/models/clip/simple_tokenizer.py
backprop/models/distiluse_base_multilingual_cased_v2/__init__.py
backprop/models/distiluse_base_multilingual_cased_v2/model.py
backprop/models/efficientnet/__init__.py
backprop/models/efficientnet/model.py
backprop/models/efficientnet/models_list.py
backprop/models/gpt2_large/__init__.py
backprop/models/gpt2_large/model.py
backprop/models/hf_causallm_tg_model/__init__.py
backprop/models/hf_causallm_tg_model/model.py
backprop/models/hf_causallm_tg_model/models_list.py
backprop/models/hf_nli_model/__init__.py
backprop/models/hf_nli_model/model.py
backprop/models/hf_nli_model/models_list.py
backprop/models/hf_seq2seq_tg_model/__init__.py
backprop/models/hf_seq2seq_tg_model/model.py
backprop/models/hf_seq2seq_tg_model/models_list.py
backprop/models/hf_seq_tc_model/__init__.py
backprop/models/hf_seq_tc_model/model.py
backprop/models/hf_seq_tc_model/models_list.py
backprop/models/msmarco_distilroberta_base_v2/__init__.py
backprop/models/msmarco_distilroberta_base_v2/model.py
backprop/models/st_model/__init__.py
backprop/models/st_model/model.py
backprop/models/st_model/models_list.py
backprop/models/t5/__init__.py
backprop/models/t5/model.py
backprop/models/t5/models_list.py
backprop/models/t5_base_qa_summary_emotion/__init__.py
backprop/models/t5_base_qa_summary_emotion/model.py
backprop/models/t5_qa_summary_emotion/__init__.py
backprop/models/t5_qa_summary_emotion/model.py
backprop/models/t5_qa_summary_emotion/models_list.py
backprop/models/xlmr_large_xnli/__init__.py
backprop/models/xlmr_large_xnli/model.py
backprop/models/xlnet/__init__.py
backprop-0.1.3.dist-info/LICENSE
backprop-0.1.3.dist-info/METADATA
backprop-0.1.3.dist-info/WHEEL
backprop-0.1.3.dist-info/top_level.txt
backprop-0.1.3.dist-info/RECORD
