Metadata-Version: 2.1
Name: backprop
Version: 0.1.3
Summary: Backprop
Home-page: https://github.com/backprop-ai/backprop
Author: Backprop
Author-email: hello@backprop.co
License: UNKNOWN
Project-URL: Bug Tracker, https://github.com/backprop-ai/backprop/issues
Project-URL: Documentation, https://backprop.readthedocs.io/en/latest/
Project-URL: Source Code, https://github.com/backprop-ai/backprop
Platform: UNKNOWN
Classifier: Programming Language :: Python :: 3
Classifier: License :: OSI Approved :: Apache Software License
Classifier: Operating System :: OS Independent
Classifier: Intended Audience :: Developers
Classifier: Topic :: Scientific/Engineering :: Artificial Intelligence
Classifier: Topic :: Scientific/Engineering :: Image Recognition
Classifier: Topic :: Scientific/Engineering :: Information Analysis
Requires-Python: >=3.6
Requires-Dist: dill
Requires-Dist: efficientnet-pytorch
Requires-Dist: ftfy
Requires-Dist: pytorch-lightning (<1.3.0,>=1.2.0)
Requires-Dist: sentence-transformers (>=0.4.1.2)
Requires-Dist: torch (<1.8.0)
Requires-Dist: torchtext (<0.9.0)
Requires-Dist: torchvision (<0.9.0)
Requires-Dist: transformers (<4.5.0,>=4.3.2)
